panpipes/__init__.py
panpipes/entry.py
panpipes/funcs.py
panpipes/version.py
panpipes/R_scripts/__init__.py
panpipes/R_scripts/install_R_libs.R
panpipes/R_scripts/plotQC.R
panpipes/R_scripts/plot_cluster_metrics.R
panpipes/R_scripts/plot_metrics.R
panpipes/R_scripts/plotclustree.R
panpipes/R_scripts/produce_barplot_10xmetric.v3.R
panpipes/R_scripts/refmap_wnn.R
panpipes/funcs/__init__.py
panpipes/funcs/io.py
panpipes/funcs/plotting.py
panpipes/funcs/processing.py
panpipes/funcs/scmethods.py
panpipes/panpipes/__init__.py
panpipes/panpipes/pipeline_clustering.py
panpipes/panpipes/pipeline_deconvolution_spatial.py
panpipes/panpipes/pipeline_ingest.py
panpipes/panpipes/pipeline_integration.py
panpipes/panpipes/pipeline_preprocess.py
panpipes/panpipes/pipeline_preprocess_spatial.py
panpipes/panpipes/pipeline_qc_spatial.py
panpipes/panpipes/pipeline_refmap.py
panpipes/panpipes/pipeline_vis.py
panpipes/panpipes/pipeline_clustering/pipeline.yml
panpipes/panpipes/pipeline_deconvolution_spatial/pipeline.yml
panpipes/panpipes/pipeline_ingest/pipeline.yml
panpipes/panpipes/pipeline_integration/pipeline.yml
panpipes/panpipes/pipeline_preprocess/pipeline.yml
panpipes/panpipes/pipeline_preprocess_spatial/pipeline.yml
panpipes/panpipes/pipeline_qc_spatial/pipeline.yml
panpipes/panpipes/pipeline_refmap/pipeline.yml
panpipes/panpipes/pipeline_vis/pipeline.yml
panpipes/python_scripts/__init__.py
panpipes/python_scripts/aggregate_cellranger_summary_metrics.py
panpipes/python_scripts/aggregate_csvs.py
panpipes/python_scripts/assess_background.py
panpipes/python_scripts/batch_correct_bbknn.py
panpipes/python_scripts/batch_correct_combat.py
panpipes/python_scripts/batch_correct_harmony.py
panpipes/python_scripts/batch_correct_merge.py
panpipes/python_scripts/batch_correct_mofa.py
panpipes/python_scripts/batch_correct_multivi.py
panpipes/python_scripts/batch_correct_none.py
panpipes/python_scripts/batch_correct_scanorama.py
panpipes/python_scripts/batch_correct_scvi.py
panpipes-1.2.0.dist-info/licenses/LICENSE
panpipes-1.2.0.dist-info/METADATA
panpipes-1.2.0.dist-info/WHEEL
panpipes-1.2.0.dist-info/entry_points.txt
panpipes-1.2.0.dist-info/top_level.txt
panpipes-1.2.0.dist-info/RECORD
