Metadata-Version: 2.4
Name: panpipes
Version: 1.2.0
Summary: Panpipes - multimodal single cell pipelines
Author: Charlotte Rich-Griffin, Fabiola Curion
Classifier: License :: OSI Approved :: BSD License
Classifier: Development Status :: 3 - Alpha
Classifier: Intended Audience :: Science/Research
Classifier: Programming Language :: Python :: 3
Classifier: Programming Language :: R
Requires-Python: >=3.10
License-File: LICENSE
Requires-Dist: jax
Requires-Dist: jaxlib
Requires-Dist: apsw
Requires-Dist: bbknn
Requires-Dist: cgatcore
Requires-Dist: drmaa
Requires-Dist: gevent
Requires-Dist: harmonypy
Requires-Dist: mofapy2
Requires-Dist: muon
Requires-Dist: matplotlib
Requires-Dist: openpyxl
Requires-Dist: paramiko
Requires-Dist: pysam
Requires-Dist: pyyaml
Requires-Dist: ruffus
Requires-Dist: scanorama
Requires-Dist: scanpy
Requires-Dist: seaborn
Requires-Dist: leidenalg
Requires-Dist: louvain
Requires-Dist: scib
Requires-Dist: scib-metrics
Requires-Dist: scikit-misc
Requires-Dist: scirpy
Requires-Dist: scrublet
Requires-Dist: scvi-tools
Requires-Dist: sqlalchemy
Provides-Extra: dev
Requires-Dist: packaging; extra == "dev"
Requires-Dist: pytest; extra == "dev"
Requires-Dist: twine; extra == "dev"
Requires-Dist: build; extra == "dev"
Provides-Extra: notebook
Requires-Dist: jupyter; extra == "notebook"
Requires-Dist: jupyterlab; extra == "notebook"
Provides-Extra: spatial
Requires-Dist: jax; extra == "spatial"
Requires-Dist: jaxlib; extra == "spatial"
Requires-Dist: scvi-tools; extra == "spatial"
Requires-Dist: scipy; extra == "spatial"
Requires-Dist: squidpy; extra == "spatial"
Requires-Dist: cell2location; extra == "spatial"
Requires-Dist: tangram-sc; extra == "spatial"
Requires-Dist: spatialdata; extra == "spatial"
Requires-Dist: spatialdata-io; extra == "spatial"
Requires-Dist: dask; extra == "spatial"
Provides-Extra: refmap-old
Requires-Dist: scvi-tools; extra == "refmap-old"
Requires-Dist: pandas<2.0.0; extra == "refmap-old"
Requires-Dist: scib; extra == "refmap-old"
Dynamic: license-file
